pandapipes/__init__.py
pandapipes/constants.py
pandapipes/create.py
pandapipes/deprecations.py
pandapipes/idx_branch.py
pandapipes/idx_node.py
pandapipes/pandapipes_net.py
pandapipes/pipeflow.py
pandapipes/toolbox.py
pandapipes/component_models/__init__.py
pandapipes/component_models/circulation_pump_mass_component.py
pandapipes/component_models/circulation_pump_pressure_component.py
pandapipes/component_models/component_toolbox.py
pandapipes/component_models/compressor_component.py
pandapipes/component_models/ext_grid_component.py
pandapipes/component_models/flow_control_component.py
pandapipes/component_models/heat_consumer_component.py
pandapipes/component_models/heat_exchanger_component.py
pandapipes/component_models/junction_component.py
pandapipes/component_models/mass_storage_component.py
pandapipes/component_models/pipe_component.py
pandapipes/component_models/pressure_control_component.py
pandapipes/component_models/pump_component.py
pandapipes/component_models/sink_component.py
pandapipes/component_models/source_component.py
pandapipes/component_models/valve_component.py
pandapipes/component_models/abstract_models/__init__.py
pandapipes/component_models/abstract_models/base_component.py
pandapipes/component_models/abstract_models/branch_models.py
pandapipes/component_models/abstract_models/branch_w_internals_models.py
pandapipes/component_models/abstract_models/branch_wo_internals_models.py
pandapipes/component_models/abstract_models/circulation_pump.py
pandapipes/component_models/abstract_models/const_flow_models.py
pandapipes/component_models/abstract_models/node_element_models.py
pandapipes/component_models/abstract_models/node_models.py
pandapipes/control/__init__.py
pandapipes/control/run_control.py
pandapipes/converter/stanet/__init__.py
pandapipes/converter/stanet/data_cleaning.py
pandapipes/converter/stanet/preparing_steps.py
pandapipes/converter/stanet/stanet2pandapipes.py
pandapipes/converter/stanet/table_creation.py
pandapipes-0.13.0.dist-info/licenses/LICENSE
pandapipes-0.13.0.dist-info/METADATA
pandapipes-0.13.0.dist-info/WHEEL
pandapipes-0.13.0.dist-info/top_level.txt
pandapipes-0.13.0.dist-info/RECORD
