Metadata-Version: 2.4
Name: pandapipes
Version: 0.13.0
Summary: A pipeflow calculation tool that complements pandapower in the simulation of multi energy grids
Author-email: Simon Ruben Drauz-Mauel <simon.ruben.drauz-mauel@iee.fraunhofer.de>, Daniel Lohmeier <daniel.lohmeier@retoflow.de>, Jolando Marius Kisse <jolando.kisse@uni-kassel.de>, Erik Prade <erik.prade@iee.fraunhofer.de>
License: Copyright (c) 2020-2026 by Fraunhofer Institute for Energy Economics
Project-URL: Homepage, https://www.pandapipes.org
Project-URL: Documentation, https://pandapipes.readthedocs.io
Project-URL: Source, https://github.com/e2nIEE/pandapipes
Project-URL: Repository, https://github.com/e2nIEE/pandapipes.git
Project-URL: Issues, https://github.com/e2nIEE/pandapipes/issues
Project-URL: Download, https://pypi.org/project/pandapipes/#files
Project-URL: Changelog, https://github.com/e2nIEE/pandapipes/blob/develop/CHANGELOG.rst
Keywords: network,analysis,optimization,automation,grid,energy,engineering,simulation,pipeflow,pandapipes,gas
Classifier: Development Status :: 5 - Production/Stable
Classifier: Environment :: Console
Classifier: Intended Audience :: Developers
Classifier: Intended Audience :: Education
Classifier: Intended Audience :: Science/Research
Classifier: License :: OSI Approved :: BSD License
Classifier: Natural Language :: English
Classifier: Operating System :: OS Independent
Classifier: Programming Language :: Python
Classifier: Programming Language :: Python :: 3
Classifier: Programming Language :: Python :: 3.9
Classifier: Programming Language :: Python :: 3.10
Classifier: Programming Language :: Python :: 3.11
Classifier: Programming Language :: Python :: 3.12
Requires-Python: >=3.10
License-File: LICENSE
Requires-Dist: pandapower==3.3.0
Requires-Dist: matplotlib
Requires-Dist: shapely
Provides-Extra: docs
Requires-Dist: numpydoc>=1.5.0; extra == "docs"
Requires-Dist: sphinx>=5.3.0; extra == "docs"
Requires-Dist: sphinx_rtd_theme>=1.1.1; extra == "docs"
Requires-Dist: sphinxcontrib.bibtex>=2.5.0; extra == "docs"
Requires-Dist: sphinx-pyproject; extra == "docs"
Provides-Extra: plotting
Requires-Dist: plotly; extra == "plotting"
Requires-Dist: igraph; extra == "plotting"
Provides-Extra: test
Requires-Dist: pytest; extra == "test"
Requires-Dist: pytest-xdist; extra == "test"
Requires-Dist: pytest-split; extra == "test"
Requires-Dist: nbmake; extra == "test"
Requires-Dist: numba; extra == "test"
Requires-Dist: setuptools; python_version >= "3.12" and extra == "test"
Provides-Extra: fileio
Requires-Dist: pandapower[fileio]; extra == "fileio"
Provides-Extra: all
Requires-Dist: pandapipes[docs,fileio,plotting,test]; extra == "all"
Dynamic: license-file
